{"cameraMode":{"drawMode":0,"name":"Shaded","section":"Shading Mode"},"sceneLighting":false,"audioPlay":false,"sceneViewState":{"m_AlwaysRefresh":false,"showFog":true,"showSkybox":false,"showFlares":true,"showImageEffects":true,"showParticleSystems":true,"showVisualEffectGraphs":true,"m_FxEnabled":true},"in2DMode":false,"pivot":{"x":-12.449384689331055,"y":13.844707489013672,"z":-20.134096145629884},"rotation":{"x":0.18457753956317902,"y":0.687005341053009,"z":-0.1871778815984726,"w":0.6774535775184631},"size":13.670234680175782,"orthographic":false}